{
  "mode": "pre",
  "tag": "rc",
  "initialVersions": {
    "elevenlabs-react-native-example": "1.0.3",
    "@elevenlabs/agents-cli": "0.6.2",
    "@elevenlabs/client": "0.14.0",
    "@elevenlabs/convai-widget-core": "0.9.0",
    "@elevenlabs/convai-widget-embed": "0.9.0",
    "@elevenlabs/react": "0.14.0",
    "@elevenlabs/react-native": "0.5.10",
    "@elevenlabs/types": "0.5.0",
    "@elevenlabs/typescript-config": "0.0.0"
  },
  "changesets": [
    "client-input-class-removed",
    "client-input-output-controller-interfaces",
    "conversation-namespace-object",
    "fix-volume-no-throw",
    "fix-wix-compat",
    "infer-connection-type-from-mode",
    "output-controller-breaking",
    "react-controlled-mute-state",
    "react-conversation-context-api",
    "react-device-format-config-output-device",
    "react-export-conversation-status",
    "react-granular-conversation-hooks",
    "react-native-rewrite",
    "react-use-conversation-client-tool",
    "replace-microbundle-with-rolldown",
    "types-callback-keys",
    "voice-conversation-wakelock-private"
  ]
}
